earthranger_utils/__init__.py
earthranger_utils/attach_image_er.py
earthranger_utils/get_cam_location.py
earthranger_utils/post_cougar_log.py
earthranger_utils/post_event_er.py
earthranger_utils-1.0.1.dist-info/LICENSE.txt
earthranger_utils-1.0.1.dist-info/METADATA
earthranger_utils-1.0.1.dist-info/WHEEL
earthranger_utils-1.0.1.dist-info/top_level.txt
earthranger_utils-1.0.1.dist-info/RECORD
